agent_recipes/__init__.py
agent_recipes/opencode_parity/__init__.py
agent_recipes/opencode_parity/event_bus_example.py
agent_recipes/opencode_parity/permissions_example.py
agent_recipes/recipe_runtime/__init__.py
agent_recipes/recipe_runtime/core.py
agent_recipes/templates/ai-ab-hook-tester/recipe.yaml
agent_recipes/templates/ai-ab-hook-tester/tools.py
agent_recipes/templates/ai-angle-generator/recipe.yaml
agent_recipes/templates/ai-angle-generator/tools.py
agent_recipes/templates/ai-api-doc-generator/README.md
agent_recipes/templates/ai-api-doc-generator/TEMPLATE.yaml
agent_recipes/templates/ai-api-tester/README.md
agent_recipes/templates/ai-api-tester/TEMPLATE.yaml
agent_recipes/templates/ai-audio-enhancer/README.md
agent_recipes/templates/ai-audio-enhancer/TEMPLATE.yaml
agent_recipes/templates/ai-audio-normalizer/README.md
agent_recipes/templates/ai-audio-normalizer/TEMPLATE.yaml
agent_recipes/templates/ai-audio-splitter/README.md
agent_recipes/templates/ai-audio-splitter/TEMPLATE.yaml
agent_recipes/templates/ai-background-music-generator/README.md
agent_recipes/templates/ai-background-music-generator/TEMPLATE.yaml
agent_recipes/templates/ai-background-remover/README.md
agent_recipes/templates/ai-background-remover/TEMPLATE.yaml
agent_recipes/templates/ai-barcode-scanner/README.md
agent_recipes/templates/ai-barcode-scanner/TEMPLATE.yaml
agent_recipes/templates/ai-blog-generator/README.md
agent_recipes/templates/ai-blog-generator/TEMPLATE.yaml
agent_recipes/templates/ai-brief-generator/recipe.yaml
agent_recipes/templates/ai-brief-generator/tools.py
agent_recipes/templates/ai-brief-generator/__pycache__/tools.cpython-312.pyc
agent_recipes/templates/ai-broll-builder/recipe.yaml
agent_recipes/templates/ai-broll-builder/tools.py
agent_recipes/templates/ai-calendar-scheduler/README.md
agent_recipes/templates/ai-calendar-scheduler/TEMPLATE.yaml
agent_recipes/templates/ai-changelog-generator/README.md
agent_recipes/templates/ai-changelog-generator/TEMPLATE.yaml
agent_recipes-0.0.12.dist-info/METADATA
agent_recipes-0.0.12.dist-info/WHEEL
agent_recipes-0.0.12.dist-info/top_level.txt
agent_recipes-0.0.12.dist-info/RECORD
