Metadata-Version: 2.4
Name: agent-recipes
Version: 0.0.12
Summary: Real-world AI agent templates and recipes for PraisonAI
Author: praison
License: Apache-2.0
Project-URL: Homepage, https://github.com/MervinPraison/agent-recipes
Project-URL: Documentation, https://docs.praison.ai/templates
Project-URL: Repository, https://github.com/MervinPraison/agent-recipes
Project-URL: Issues, https://github.com/MervinPraison/agent-recipes/issues
Keywords: ai,agents,templates,recipes,praisonai,workflow
Classifier: Development Status :: 4 - Beta
Classifier: Intended Audience :: Developers
Classifier: License :: OSI Approved :: Apache Software License
Classifier: Programming Language :: Python :: 3
Classifier: Programming Language :: Python :: 3.9
Classifier: Programming Language :: Python :: 3.10
Classifier: Programming Language :: Python :: 3.11
Classifier: Programming Language :: Python :: 3.12
Classifier: Topic :: Scientific/Engineering :: Artificial Intelligence
Requires-Python: >=3.9
Requires-Dist: pyyaml>=6.0
Provides-Extra: transcript
Requires-Dist: openai-whisper>=20231117; extra == "transcript"
Requires-Dist: yt-dlp>=2023.11.16; extra == "transcript"
Provides-Extra: video
Requires-Dist: moviepy>=1.0.3; extra == "video"
Requires-Dist: ffmpeg-python>=0.2.0; extra == "video"
Provides-Extra: all
Requires-Dist: agent-recipes[transcript,video]; extra == "all"
Provides-Extra: dev
Requires-Dist: pytest>=7.0; extra == "dev"
Requires-Dist: pytest-cov>=4.0; extra == "dev"
